LICENSE
twang/__init__.py
twang/source_separation/__init__.py
twang/source_separation/base.py
twang/source_separation/demucs.py
twang/source_separation/librosa.py
twang/source_separation/nussl.py
twang/track/__init__.py
twang/track/base.py
twang/types.py
twang/util/__init__.py
twang/util/audio.py
twang/util/file_util.py
twang/util/time.py
twang-0.0.2.dist-info/LICENSE
twang-0.0.2.dist-info/METADATA
twang-0.0.2.dist-info/WHEEL
twang-0.0.2.dist-info/RECORD
