Metadata-Version: 2.1
Name: twang
Version: 0.0.2
Summary: Machine learning tools for guitarists
Home-page: https://github.com/michaelhball/twang
License: MIT
Author: mhsb
Author-email: michael.h.s.ball@gmail.com
Requires-Python: >=3.8,<4.0
Classifier: License :: OSI Approved :: MIT License
Classifier: Programming Language :: Python :: 3
Classifier: Programming Language :: Python :: 3.8
Classifier: Programming Language :: Python :: 3.9
Classifier: Programming Language :: Python :: 3.10
Classifier: Programming Language :: Python :: 3.11
Classifier: Programming Language :: Python :: 3.12
Requires-Dist: Cython (>=0.29.33,<0.30.0)
Requires-Dist: ipython (>=8.10.0,<9.0.0)
Requires-Dist: librosa (>=0.10.1,<0.11.0)
Requires-Dist: mido (>=1.2.10,<2.0.0)
Requires-Dist: pre-commit (>=2.20.0,<3.0.0)
Requires-Dist: pydub (>=0.25.1,<0.26.0)
Requires-Dist: ruff (>=0.1.8,<0.2.0)
Project-URL: Repository, https://github.com/michaelhball/twang
